{
    
    "orders" : [{"id" : 101,
		 "products" : [ {
       				 "id": 11,
       				 "price" : 10000,
       				 "name" : "Moto G6+",
       				 "desc" : "",
        			 "img" : ""
      				}, 
                                {
       				  "id": 12,
       				  "price" : 12000,
       				  "name" : "Samsung M30",
        			  "desc" : "",
        			  "img" : ""
      				}, 
      				{
       				  "id": 13,
        			  "price" : 9000,
       				  "name" : "MOTO G5",
       				  "desc" : "",
        			  "img" : ""
      				}, 
      				{
      				  "id": 14,
       				  "price" : 40000,
       				  "name" : "iPhone 8",
       				  "desc" : "",
        			  "img" : ""
      				}, 
      				{
       				  "id": 15,
        			  "price" : 16,
       				  "name" : "Andy",
       				  "desc" : "",
       				  "img" : ""
      				}
      
    		               ]
   
  		  },
		  {"id" : 102,
		   "products" : [ {
       				 "id": 21,
       				 "price" : 10000,
       				 "name" : "Moto G6+",
       				 "desc" : "",
        			 "img" : ""
      				}, 
                                {
       				  "id": 22,
       				  "price" : 12000,
       				  "name" : "Samsung M30",
        			  "desc" : "",
        			  "img" : ""
      				}, 
      				{
       				  "id": 23,
        			  "price" : 9000,
       				  "name" : "MOTO G5",
       				  "desc" : "",
        			  "img" : ""
      				}, 
      				{
      				  "id": 24,
       				  "price" : 40000,
       				  "name" : "iPhone 8",
       				  "desc" : "",
        			  "img" : ""
      				}, 
      				{
       				  "id": 21,
        			  "price" : 16,
       				  "name" : "Andy",
       				  "desc" : "",
       				  "img" : ""
      				}
      
    		               ]
   
  		  }	

                ]
}